karrio/mappers/tnt/__init__.py
karrio/mappers/tnt/mapper.py
karrio/mappers/tnt/proxy.py
karrio/mappers/tnt/settings.py
karrio/plugins/tnt/__init__.py
karrio/providers/tnt/__init__.py
karrio/providers/tnt/error.py
karrio/providers/tnt/rate.py
karrio/providers/tnt/tracking.py
karrio/providers/tnt/units.py
karrio/providers/tnt/utils.py
karrio/providers/tnt/shipment/__init__.py
karrio/providers/tnt/shipment/create.py
karrio/schemas/tnt/__init__.py
karrio/schemas/tnt/label_common_definitions.py
karrio/schemas/tnt/label_request.py
karrio/schemas/tnt/label_response.py
karrio/schemas/tnt/rating_common_definitions.py
karrio/schemas/tnt/rating_request.py
karrio/schemas/tnt/rating_response.py
karrio/schemas/tnt/shipping_common_definitions.py
karrio/schemas/tnt/shipping_request.py
karrio/schemas/tnt/shipping_response.py
karrio/schemas/tnt/tracking_request.py
karrio/schemas/tnt/tracking_response.py
karrio_tnt-2026.1.4.dist-info/METADATA
karrio_tnt-2026.1.4.dist-info/WHEEL
karrio_tnt-2026.1.4.dist-info/entry_points.txt
karrio_tnt-2026.1.4.dist-info/top_level.txt
karrio_tnt-2026.1.4.dist-info/RECORD
